fastrtc_jp/__init__.py
fastrtc_jp/speech_to_text/mlx_whisper.py
fastrtc_jp/speech_to_text/sr_google.py
fastrtc_jp/speech_to_text/util.py
fastrtc_jp/speech_to_text/vosk.py
fastrtc_jp/text_to_speech/gtts.py
fastrtc_jp/text_to_speech/opt.py
fastrtc_jp/text_to_speech/style_bert_vits2.py
fastrtc_jp/text_to_speech/util.py
fastrtc_jp/text_to_speech/voicevox.py
fastrtc_jp/text_to_speech/voicevox_charinfo.json
fastrtc_jp/utils/hf_util.py
fastrtc_jp/utils/util.py
fastrtc_jp-0.1.5.dist-info/licenses/LICENSE
fastrtc_jp-0.1.5.dist-info/METADATA
fastrtc_jp-0.1.5.dist-info/WHEEL
fastrtc_jp-0.1.5.dist-info/top_level.txt
fastrtc_jp-0.1.5.dist-info/RECORD
